screenreaderx/__init__.py
screenreaderx/__main__.py
screenreaderx-1.0.0.dist-info/METADATA
screenreaderx-1.0.0.dist-info/WHEEL
screenreaderx-1.0.0.dist-info/entry_points.txt
screenreaderx-1.0.0.dist-info/top_level.txt
screenreaderx-1.0.0.dist-info/RECORD
